vkl/__init__.py
vkl-2018.02.03.03.dist-info/DESCRIPTION.rst
vkl-2018.02.03.03.dist-info/METADATA
vkl-2018.02.03.03.dist-info/RECORD
vkl-2018.02.03.03.dist-info/WHEEL
vkl-2018.02.03.03.dist-info/entry_points.txt
vkl-2018.02.03.03.dist-info/metadata.json
vkl-2018.02.03.03.dist-info/top_level.txt
