Metadata-Version: 2.0
Name: vkl
Version: 2018.02.03.03
Summary: vkl - a better ls-experience
Home-page: https://github.com/novoid/vkl
Author: Karl Voit
Author-email: tools@Karl-Voit.at
License: UNKNOWN
Download-URL: https://github.com/novoid/vkl/zipball/master
Keywords: file managing,file management,files,shell
Platform: UNKNOWN
Classifier: Programming Language :: Python :: 3 :: Only
Classifier: Development Status :: 5 - Production/Stable
Classifier: Environment :: Console
Classifier: Intended Audience :: End Users/Desktop
Classifier: License :: OSI Approved :: GNU General Public License (GPL)
Classifier: Operating System :: OS Independent
